[
    {
        "url": "https://www.tecmundo.com.br/mercado/407157-home-office-117-vagas-para-trabalho-remoto-1809.htm",
        "title": "Home office: 117 vagas para trabalho remoto [18/09]",
        "description": "São vagas mais de 100 vagas remotas em diversas áreas como Tecnologia, Marketing, Design, Produto, entre outras: confira a lista!",
        "image": "https://tm.ibxk.com.br/2025/09/18/18084257830002.jpg",
        "date": null
    },
    {
        "url": "https://www.tecmundo.com.br/minha-serie/602143-marvel-confirma-o-destino-de-demolidor-renascido-antes-do-lancamento-da-2-temporada.htm",
        "title": "Marvel confirma o destino de “Demolidor: Renascido” antes do lançamento da 2ª temporada",
        "description": "Demolidor: Renascido vai ir muito além dos eventos de sua segunda parte",
        "image": "https://tm.ibxk.com.br/2025/09/18/18140301169036.jpg",
        "date": null
    }
]